{"nodes": [{"id": "pi_readme_pi_bridge", "label": "Raspberry Pi Bridge Service", "file_type": "document", "source_file": "pi/README.md", "source_location": "line 1", "source_url": null, "captured_at": null, "author": null, "contributor": null}, {"id": "pi_readme_fastapi_server", "label": "FastAPI Server (main.py)", "file_type": "concept", "source_file": "pi/README.md", "source_location": "line 62", "source_url": null, "captured_at": null, "author": null, "contributor": null}, {"id": "pi_readme_bambu_client", "label": "Bambu Client (FTPS + MQTT)", "file_type": "concept", "source_file": "pi/README.md", "source_location": "line 63", "source_url": null, "captured_at": null, "author": null, "contributor": null}, {"id": "pi_readme_cloudflare_tunnel", "label": "Cloudflare Tunnel (cloudflared)", "file_type": "concept", "source_file": "pi/README.md", "source_location": "line 64", "source_url": null, "captured_at": null, "author": null, "contributor": null}], "edges": [{"source": "pi_readme_pi_bridge", "target": "pi_readme_fastapi_server", "relation": "references", "confidence": "EXTRACTED", "confidence_score": 1.0, "source_file": "pi/README.md", "source_location": "line 62", "weight": 1.0}, {"source": "pi_readme_pi_bridge", "target": "pi_readme_bambu_client", "relation": "references", "confidence": "EXTRACTED", "confidence_score": 1.0, "source_file": "pi/README.md", "source_location": "line 63", "weight": 1.0}, {"source": "pi_readme_pi_bridge", "target": "pi_readme_cloudflare_tunnel", "relation": "references", "confidence": "EXTRACTED", "confidence_score": 1.0, "source_file": "pi/README.md", "source_location": "line 64", "weight": 1.0}, {"source": "pi_readme_cloudflare_tunnel", "target": "readme_cloudflare_workers_backend", "relation": "conceptually_related_to", "confidence": "INFERRED", "confidence_score": 0.85, "source_file": "pi/README.md", "source_location": null, "weight": 0.85}], "hyperedges": [{"id": "pi_bridge_stack", "label": "Pi Bridge Runtime Stack (FastAPI + Bambu MQTT + Cloudflare Tunnel)", "nodes": ["pi_readme_fastapi_server", "pi_readme_bambu_client", "pi_readme_cloudflare_tunnel"], "relation": "form", "confidence": "EXTRACTED", "confidence_score": 1.0, "source_file": "pi/README.md"}]}